video_toolkit/SrtToCsv.py
video_toolkit/Video01.py
video_toolkit/__init__.py
video_toolkit/archive01.py
video_toolkit/cant_use_vt.py
video_toolkit/ffmpeg_create.py
video_toolkit/ffmpeg_extract.py
video_toolkit/fix_bug_vt.py
video_toolkit/sandbox1_vt.py
video_toolkit/utils.py
video_toolkit/utils_vt.py
video_toolkit/whisper.py
video_toolkit-0.1.2.dist-info/METADATA
video_toolkit-0.1.2.dist-info/WHEEL
video_toolkit-0.1.2.dist-info/top_level.txt
video_toolkit-0.1.2.dist-info/RECORD
