Metadata-Version: 2.1
Name: video_toolkit
Version: 0.1.2
Summary: package to help you with extraction of video information eg audio, subtitle
Author: Dear Norathee
License: MIT
Requires-Python: >=3.10.0
Requires-Dist: os-toolkit >=0.1.1
Requires-Dist: dataframe-short >=0.1.6
Requires-Dist: python-wizard >=0.1.2
Requires-Dist: inspect-py >=0.1.1
Requires-Dist: py-string-tool >=0.1.3
Requires-Dist: pandas
Requires-Dist: seaborn
Requires-Dist: pysrt
Requires-Dist: pydub
Requires-Dist: playsound
Requires-Dist: tqdm
Requires-Dist: pycountry
Requires-Dist: lingtrain-aligner
Requires-Dist: ffmpeg
Requires-Dist: fuzzywuzzy
Requires-Dist: pysubs2
Provides-Extra: full
Requires-Dist: torch >=1.0 ; extra == 'full'
